{
  "shape": "Point",
  "rate": 120.0,
  "burst": null,
  "lifetime": [
    0.3,
    0.8
  ],
  "initial_speed": [
    40.0,
    100.0
  ],
  "spread_angle": 0.5,
  "direction": 1.5707964,
  "gravity": [
    0.0,
    20.0
  ],
  "size_start": [
    10.0,
    20.0
  ],
  "size_over_life": {
    "points": [
      [
        0.0,
        1.0
      ],
      [
        1.0,
        0.0
      ]
    ]
  },
  "color_over_life": {
    "stops": [
      [
        0.0,
        [
          1.0,
          0.9,
          0.2,
          1.0
        ]
      ],
      [
        0.3,
        [
          1.0,
          0.4,
          0.0,
          0.9
        ]
      ],
      [
        0.7,
        [
          0.8,
          0.1,
          0.0,
          0.5
        ]
      ],
      [
        1.0,
        [
          0.3,
          0.0,
          0.0,
          0.0
        ]
      ]
    ]
  },
  "rotation_speed": [
    0.0,
    0.0
  ],
  "blend_mode": "Alpha",
  "on_death": null
}